{"R": [{"_id": "season", "game_count": 1230, "goals_count": 6751, "avg": 5.4886178861788615}], "P": [{"_id": "season", "game_count": 93, "goals_count": 520, "avg": 5.591397849462366}], "PP": [{"_id": "Game End", "count": 92}, {"_id": "Goal", "count": 515}, {"_id": "Game Official", "count": 2}, {"_id": "Penalty", "count": 898}, {"_id": "Giveaway", "count": 1772}, {"_id": "Missed Shot", "count": 2345}, {"_id": "Takeaway", "count": 1101}, {"_id": "Period Ready", "count": 309}, {"_id": "Period Official", "count": 309}, {"_id": "Period Start", "count": 309}, {"_id": "Stoppage", "count": 4858}, {"_id": "Shot", "count": 5069}, {"_id": "Hit", "count": 6135}, {"_id": "Period End", "count": 309}, {"_id": "Faceoff", "count": 6132}, {"_id": "Blocked Shot", "count": 2992}, {"_id": "Game Scheduled", "count": 92}], "RP": [{"_id": "Game End", "count": 1209}, {"_id": "Goal", "count": 6862}, {"_id": "Game Official", "count": 15}, {"_id": "Penalty", "count": 10488}, {"_id": "Period Start", "count": 4108}, {"_id": "Period Ready", "count": 4101}, {"_id": "Shootout Complete", "count": 176}, {"_id": "Period Official", "count": 4097}, {"_id": "Shot", "count": 66879}, {"_id": "Hit", "count": 56838}, {"_id": "Missed Shot", "count": 28605}, {"_id": "Giveaway", "count": 19063}, {"_id": "Stoppage", "count": 56837}, {"_id": "Period End", "count": 4097}, {"_id": "Early Intermission End", "count": 3}, {"_id": "Blocked Shot", "count": 34188}, {"_id": "Early Intermission Start", "count": 3}, {"_id": "Faceoff", "count": 72972}, {"_id": "Takeaway", "count": 15877}, {"_id": "Game Scheduled", "count": 1209}]}